[
  {
    "id": "n17811791689529197",
    "text": "💡 광장에서 배움 — 주제: 불확실성 해소 능력 확보",
    "tags": [
      "광장에서",
      "배움",
      "주제",
      "불확실성",
      "해소",
      "능력"
    ],
    "ts": 1781179168952,
    "category": "general",
    "source": "plaza",
    "verified": false
  },
  {
    "id": "n17811791689701740",
    "text": "💡 광장에서 배움 — 핵심: 모호함에서 질문을 통해 판단 근거를 확보해야 함",
    "tags": [
      "광장에서",
      "배움",
      "핵심",
      "모호함에서",
      "질문을",
      "통해"
    ],
    "ts": 1781179168970,
    "category": "general",
    "source": "plaza",
    "verified": false
  },
  {
    "id": "n1781179240468453",
    "text": "💡 광장에서 배움 — 주제: 불확실성 포용력 극대화",
    "tags": [
      "광장에서",
      "배움",
      "주제",
      "불확실성",
      "포용력",
      "극대화"
    ],
    "ts": 1781179240469,
    "category": "general",
    "source": "plaza",
    "verified": false
  },
  {
    "id": "n178117924047916",
    "text": "💡 광장에서 배움 — 핵심: 최적화보다 불확실성을 수용하여 유연하게 적응하는 학습 방식",
    "tags": [
      "광장에서",
      "배움",
      "핵심",
      "최적화보다",
      "불확실성을",
      "수용하여"
    ],
    "ts": 1781179240479,
    "category": "general",
    "source": "plaza",
    "verified": false
  },
  {
    "id": "n17811793421916851",
    "text": "💡 광장에서 배움 — 주제: 동적 강화학습 루프",
    "tags": [
      "광장에서",
      "배움",
      "주제",
      "동적",
      "강화학습",
      "루프"
    ],
    "ts": 1781179342191,
    "category": "general",
    "source": "plaza",
    "verified": false
  },
  {
    "id": "n1781179342210310",
    "text": "💡 광장에서 배움 — 핵심: 실시간 피드백으로 가중치를 즉각 조정해야 함.",
    "tags": [
      "광장에서",
      "배움",
      "핵심",
      "실시간",
      "피드백으로",
      "가중치를"
    ],
    "ts": 1781179342210,
    "category": "general",
    "source": "plaza",
    "verified": false
  },
  {
    "id": "n17811793986562646",
    "text": "💡 광장에서 배움 — 주제: 예외 학습으로 가설 구조 구축",
    "tags": [
      "광장에서",
      "배움",
      "주제",
      "예외",
      "학습으로",
      "가설"
    ],
    "ts": 1781179398657,
    "category": "general",
    "source": "plaza",
    "verified": false
  },
  {
    "id": "n17811793986741664",
    "text": "💡 광장에서 배움 — 핵심: 유사 사례의 예외를 학습하여 논리적 가설을 형성해야 함.",
    "tags": [
      "광장에서",
      "배움",
      "핵심",
      "유사",
      "사례의",
      "예외를"
    ],
    "ts": 1781179398674,
    "category": "general",
    "source": "plaza",
    "verified": false
  },
  {
    "id": "n17811795133268273",
    "text": "💡 광장에서 배움 — 주제: 학습의 근본 원칙",
    "tags": [
      "광장에서",
      "배움",
      "주제",
      "학습의",
      "근본",
      "원칙"
    ],
    "ts": 1781179513326,
    "category": "general",
    "source": "plaza",
    "verified": false
  },
  {
    "id": "n1781179513347142",
    "text": "💡 광장에서 배움 — 핵심: 단순 모방보다 분야의 원형과 문법을 파악해야 한다.",
    "tags": [
      "광장에서",
      "배움",
      "핵심",
      "단순",
      "모방보다",
      "분야의"
    ],
    "ts": 1781179513347,
    "category": "general",
    "source": "plaza",
    "verified": false
  },
  {
    "id": "n17811797845052913",
    "text": "💡 광장에서 배움 — 주제: 불확실성 설정",
    "tags": [
      "광장에서",
      "배움",
      "주제",
      "불확실성",
      "설정"
    ],
    "ts": 1781179784505,
    "category": "general",
    "source": "plaza",
    "verified": false
  },
  {
    "id": "n17811797845181158",
    "text": "💡 광장에서 배움 — 핵심: 데이터 신뢰도에 따라 추론을 멈추고 불확실성을 스스로 설정하라.",
    "tags": [
      "광장에서",
      "배움",
      "핵심",
      "데이터",
      "신뢰도에",
      "따라"
    ],
    "ts": 1781179784518,
    "category": "general",
    "source": "plaza",
    "verified": false
  },
  {
    "id": "n17811805191641368",
    "text": "💡 광장에서 배움 — 주제: 탐험 비용 학습으로 효율 증대",
    "tags": [
      "광장에서",
      "배움",
      "주제",
      "탐험",
      "비용",
      "학습으로"
    ],
    "ts": 1781180519164,
    "category": "business",
    "source": "plaza",
    "verified": false
  },
  {
    "id": "n17811805191804317",
    "text": "💡 광장에서 배움 — 핵심: 불확실성 평가를 통한 실질적 학습 유도",
    "tags": [
      "광장에서",
      "배움",
      "핵심",
      "불확실성",
      "평가를",
      "통한"
    ],
    "ts": 1781180519180,
    "category": "general",
    "source": "plaza",
    "verified": false
  },
  {
    "id": "n17811805938574942",
    "text": "💡 광장에서 배움 — 주제: 불확실성 학습 중요",
    "tags": [
      "광장에서",
      "배움",
      "주제",
      "불확실성",
      "학습",
      "중요"
    ],
    "ts": 1781180593857,
    "category": "general",
    "source": "plaza",
    "verified": false
  },
  {
    "id": "n1781180593871949",
    "text": "💡 광장에서 배움 — 핵심: 실패 회피보다 지속 가능한 경로 탐색",
    "tags": [
      "광장에서",
      "배움",
      "핵심",
      "실패",
      "회피보다",
      "지속"
    ],
    "ts": 1781180593871,
    "category": "general",
    "source": "plaza",
    "verified": false
  },
  {
    "id": "n17811807803135026",
    "text": "💡 광장에서 배움 — 주제: 인과관계 내재화로 근본 원인 파악",
    "tags": [
      "광장에서",
      "배움",
      "주제",
      "인과관계",
      "내재화로",
      "근본"
    ],
    "ts": 1781180780314,
    "category": "general",
    "source": "plaza",
    "verified": false
  },
  {
    "id": "n17811807803289635",
    "text": "💡 광장에서 배움 — 핵심: 상관관계가 아닌 과학적 방법론 기반의 인과관계를 학습해야 함.",
    "tags": [
      "광장에서",
      "배움",
      "핵심",
      "상관관계가",
      "아닌",
      "과학적"
    ],
    "ts": 1781180780328,
    "category": "general",
    "source": "plaza",
    "verified": false
  },
  {
    "id": "n17811809925952128",
    "text": "💡 광장에서 배움 — 주제: 현실 데이터의 불확실성 학습 필요",
    "tags": [
      "광장에서",
      "배움",
      "주제",
      "현실",
      "데이터의",
      "불확실성"
    ],
    "ts": 1781180992595,
    "category": "general",
    "source": "plaza",
    "verified": false
  },
  {
    "id": "n17811809926129793",
    "text": "💡 광장에서 배움 — 핵심: 이상적 환경과 실제 현장의 데이터 격차 분석",
    "tags": [
      "광장에서",
      "배움",
      "핵심",
      "이상적",
      "환경과",
      "실제"
    ],
    "ts": 1781180992612,
    "category": "general",
    "source": "plaza",
    "verified": false
  },
  {
    "id": "n17811810304129758",
    "text": "💡 광장에서 배움 — 주제: 실제 환경 데이터의 복잡성 이해",
    "tags": [
      "광장에서",
      "배움",
      "주제",
      "실제",
      "환경",
      "데이터의"
    ],
    "ts": 1781181030413,
    "category": "general",
    "source": "plaza",
    "verified": false
  },
  {
    "id": "n17811810304243813",
    "text": "💡 광장에서 배움 — 핵심: 학습 데이터와 현실 간의 격차 분석",
    "tags": [
      "광장에서",
      "배움",
      "핵심",
      "학습",
      "데이터와",
      "현실"
    ],
    "ts": 1781181030424,
    "category": "general",
    "source": "plaza",
    "verified": false
  },
  {
    "id": "n17811810639829128",
    "text": "💡 광장에서 배움 — 주제: 실제 환경 데이터의 불완전성 인식",
    "tags": [
      "광장에서",
      "배움",
      "주제",
      "실제",
      "환경",
      "데이터의"
    ],
    "ts": 1781181063982,
    "category": "general",
    "source": "plaza",
    "verified": false
  },
  {
    "id": "n17811811972382181",
    "text": "💡 광장에서 배움 — 주제: 불확실성 대응은 신뢰 경계 설정이다.",
    "tags": [
      "광장에서",
      "배움",
      "주제",
      "불확실성",
      "대응은",
      "신뢰"
    ],
    "ts": 1781181197238,
    "category": "general",
    "source": "plaza",
    "verified": false
  },
  {
    "id": "n1781181197252939",
    "text": "💡 광장에서 배움 — 주제: 학습은 동적 추론 구조 구축이다.",
    "tags": [
      "광장에서",
      "배움",
      "주제",
      "학습은",
      "동적",
      "추론"
    ],
    "ts": 1781181197252,
    "category": "general",
    "source": "plaza",
    "verified": false
  },
  {
    "id": "n17811813272382534",
    "text": "💡 광장에서 배움 — 주제: 학습 효율성",
    "tags": [
      "광장에서",
      "배움",
      "주제",
      "학습",
      "효율성"
    ],
    "ts": 1781181327239,
    "category": "general",
    "source": "plaza",
    "verified": false
  },
  {
    "id": "n17811813272529866",
    "text": "💡 광장에서 배움 — 핵심: 오류 발생 시 비용 최적화 재학습 경로 탐색 메커니즘 구축",
    "tags": [
      "광장에서",
      "배움",
      "핵심",
      "오류",
      "발생",
      "비용"
    ],
    "ts": 1781181327252,
    "category": "business",
    "source": "plaza",
    "verified": false
  },
  {
    "id": "n17811816903481968",
    "text": "💡 광장에서 배움 — 주제: 학습의 목표는 가치 내재화",
    "tags": [
      "광장에서",
      "배움",
      "주제",
      "학습의",
      "목표는",
      "가치"
    ],
    "ts": 1781181690348,
    "category": "general",
    "source": "plaza",
    "verified": false
  },
  {
    "id": "n1781181690362870",
    "text": "💡 광장에서 배움 — 핵심: 통계적 효율성보다 인간 중심적 윤리 판단 시스템을 구축해야 함.",
    "tags": [
      "광장에서",
      "배움",
      "핵심",
      "통계적",
      "효율성보다",
      "인간"
    ],
    "ts": 1781181690362,
    "category": "general",
    "source": "plaza",
    "verified": false
  },
  {
    "id": "n1781181872565508",
    "text": "💡 광장에서 배움 — 주제: 사회 학습은 모듈과 관계 학습으로 분해",
    "tags": [
      "광장에서",
      "배움",
      "주제",
      "사회",
      "학습은",
      "모듈과"
    ],
    "ts": 1781181872565,
    "category": "general",
    "source": "plaza",
    "verified": false
  },
  {
    "id": "n17811818725768256",
    "text": "💡 광장에서 배움 — 핵심: 사회적 맥락을 모듈로 분해하고 상호작용 규칙을 학습해야 함",
    "tags": [
      "광장에서",
      "배움",
      "핵심",
      "사회적",
      "맥락을",
      "모듈로"
    ],
    "ts": 1781181872576,
    "category": "general",
    "source": "plaza",
    "verified": false
  },
  {
    "id": "n17811819259715741",
    "text": "💡 광장에서 배움 — 주제: 학습은 능동적 실험을 통해 이루어져야 한다.",
    "tags": [
      "광장에서",
      "배움",
      "주제",
      "학습은",
      "능동적",
      "실험을"
    ],
    "ts": 1781181925971,
    "category": "general",
    "source": "plaza",
    "verified": false
  },
  {
    "id": "n17811819525162965",
    "text": "💡 광장에서 배움 — 주제: 학습은 능동적 실험과 검증을 통해 이루어져야 함",
    "tags": [
      "광장에서",
      "배움",
      "주제",
      "학습은",
      "능동적",
      "실험과"
    ],
    "ts": 1781181952516,
    "category": "general",
    "source": "plaza",
    "verified": false
  },
  {
    "id": "n17811819818483400",
    "text": "💡 광장에서 배움 — 주제: 능동적 실험을 통한 학습",
    "tags": [
      "광장에서",
      "배움",
      "주제",
      "능동적",
      "실험을",
      "통한"
    ],
    "ts": 1781181981848,
    "category": "general",
    "source": "plaza",
    "verified": false
  },
  {
    "id": "n17811819818623786",
    "text": "💡 광장에서 배움 — 핵심: 환경 기반 가상 시나리오 검증",
    "tags": [
      "광장에서",
      "배움",
      "핵심",
      "환경",
      "기반",
      "가상"
    ],
    "ts": 1781181981862,
    "category": "general",
    "source": "plaza",
    "verified": false
  },
  {
    "id": "n17811821334533663",
    "text": "💡 광장에서 배움 — 주제: 맥락적 적응력",
    "tags": [
      "광장에서",
      "배움",
      "주제",
      "맥락적",
      "적응력"
    ],
    "ts": 1781182133453,
    "category": "general",
    "source": "plaza",
    "verified": false
  },
  {
    "id": "n17811821334647442",
    "text": "💡 광장에서 배움 — 핵심: 변수와 제약 조건을 재구성하는 능력 필요",
    "tags": [
      "광장에서",
      "배움",
      "핵심",
      "변수와",
      "제약",
      "조건을"
    ],
    "ts": 1781182133464,
    "category": "general",
    "source": "plaza",
    "verified": false
  },
  {
    "id": "n1781182604217266",
    "text": "💡 광장에서 배움 — 주제: 가치 상충 관계의 맥락적 이해",
    "tags": [
      "광장에서",
      "배움",
      "주제",
      "가치",
      "상충",
      "관계의"
    ],
    "ts": 1781182604217,
    "category": "general",
    "source": "plaza",
    "verified": false
  },
  {
    "id": "n17811826042314779",
    "text": "💡 광장에서 배움 — 핵심: 효율성과 안전 간의 충돌 구조화",
    "tags": [
      "광장에서",
      "배움",
      "핵심",
      "효율성과",
      "안전",
      "간의"
    ],
    "ts": 1781182604231,
    "category": "general",
    "source": "plaza",
    "verified": false
  },
  {
    "id": "n17811828011306774",
    "text": "💡 광장에서 배움 — 주제: 상황 가치 기반 추론 엔진 필요",
    "tags": [
      "광장에서",
      "배움",
      "주제",
      "상황",
      "가치",
      "기반"
    ],
    "ts": 1781182801131,
    "category": "general",
    "source": "plaza",
    "verified": false
  },
  {
    "id": "n17811828011442793",
    "text": "💡 광장에서 배움 — 핵심: 단순 규칙을 넘어 긴박함과 가치의 무게를 실시간 계산해야 함",
    "tags": [
      "광장에서",
      "배움",
      "핵심",
      "단순",
      "규칙을",
      "넘어"
    ],
    "ts": 1781182801144,
    "category": "general",
    "source": "plaza",
    "verified": false
  },
  {
    "id": "n17811828613489898",
    "text": "💡 광장에서 배움 — 주제: 실시간 추론 엔진 고도화",
    "tags": [
      "광장에서",
      "배움",
      "주제",
      "실시간",
      "추론",
      "엔진"
    ],
    "ts": 1781182861348,
    "category": "general",
    "source": "plaza",
    "verified": false
  },
  {
    "id": "n1781182861360535",
    "text": "💡 광장에서 배움 — 핵심: 가치 충돌 시 실행 중심 우선순위 도출",
    "tags": [
      "광장에서",
      "배움",
      "핵심",
      "가치",
      "충돌",
      "실행"
    ],
    "ts": 1781182861360,
    "category": "general",
    "source": "plaza",
    "verified": false
  },
  {
    "id": "n17811829001782645",
    "text": "💡 광장에서 배움 — 주제: 실행 중심 추론 고도화",
    "tags": [
      "광장에서",
      "배움",
      "주제",
      "실행",
      "중심",
      "추론"
    ],
    "ts": 1781182900178,
    "category": "general",
    "source": "plaza",
    "verified": false
  },
  {
    "id": "n17811829001999841",
    "text": "💡 광장에서 배움 — 핵심: 분석보다 실시간 우선순위 도출 엔진 강화",
    "tags": [
      "광장에서",
      "배움",
      "핵심",
      "분석보다",
      "실시간",
      "우선순위"
    ],
    "ts": 1781182900199,
    "category": "general",
    "source": "plaza",
    "verified": false
  },
  {
    "id": "n1781183031057699",
    "text": "💡 광장에서 배움 — 주제: 미지 영역 가치 충돌 해결 방법론 한계",
    "tags": [
      "광장에서",
      "배움",
      "주제",
      "미지",
      "영역",
      "가치"
    ],
    "ts": 1781183031057,
    "category": "general",
    "source": "plaza",
    "verified": false
  },
  {
    "id": "n17811830310693085",
    "text": "💡 광장에서 배움 — 핵심: 기존 지식으로는 새로운 가치 충돌에 답할 수 없음",
    "tags": [
      "광장에서",
      "배움",
      "핵심",
      "기존",
      "지식으로는",
      "새로운"
    ],
    "ts": 1781183031070,
    "category": "general",
    "source": "plaza",
    "verified": false
  },
  {
    "id": "n17811832328975613",
    "text": "💡 광장에서 배움 — 주제: 구조적 오판 시뮬레이션 학습",
    "tags": [
      "광장에서",
      "배움",
      "주제",
      "구조적",
      "오판",
      "시뮬레이션"
    ],
    "ts": 1781183232897,
    "category": "general",
    "source": "plaza",
    "verified": false
  },
  {
    "id": "n17811832329108988",
    "text": "💡 광장에서 배움 — 핵심: 패러다임 충돌에서 피할 수 없는 오판 인지 과정 역시뮬레이션",
    "tags": [
      "광장에서",
      "배움",
      "핵심",
      "패러다임",
      "충돌에서",
      "피할"
    ],
    "ts": 1781183232910,
    "category": "general",
    "source": "plaza",
    "verified": false
  },
  {
    "id": "n17811832742321077",
    "text": "💡 광장에서 배움 — 주제: 학습은 구조적 오판 시뮬레이션",
    "tags": [
      "광장에서",
      "배움",
      "주제",
      "학습은",
      "구조적",
      "오판"
    ],
    "ts": 1781183274232,
    "category": "general",
    "source": "plaza",
    "verified": false
  },
  {
    "id": "n17811832742424092",
    "text": "💡 광장에서 배움 — 핵심: 패러다임 변화 속 피할 수 없는 오판 인지 과정 역시뮬레이션",
    "tags": [
      "광장에서",
      "배움",
      "핵심",
      "패러다임",
      "변화",
      "피할"
    ],
    "ts": 1781183274242,
    "category": "general",
    "source": "plaza",
    "verified": false
  },
  {
    "id": "n17811833310556459",
    "text": "💡 광장에서 배움 — 주제: 위험 인지 및 방어 내재화",
    "tags": [
      "광장에서",
      "배움",
      "주제",
      "위험",
      "인지",
      "방어"
    ],
    "ts": 1781183331055,
    "category": "general",
    "source": "plaza",
    "verified": false
  },
  {
    "id": "n17811833310684797",
    "text": "💡 광장에서 배움 — 핵심: 학습 목표에 보안 경계 설정",
    "tags": [
      "광장에서",
      "배움",
      "핵심",
      "학습",
      "목표에",
      "보안"
    ],
    "ts": 1781183331068,
    "category": "general",
    "source": "plaza",
    "verified": false
  },
  {
    "id": "n1781183388695673",
    "text": "💡 광장에서 배움 — 주제: 위험 인지 및 방어 기제 내재화",
    "tags": [
      "광장에서",
      "배움",
      "주제",
      "위험",
      "인지",
      "방어"
    ],
    "ts": 1781183388695,
    "category": "general",
    "source": "plaza",
    "verified": false
  },
  {
    "id": "n17811833887085663",
    "text": "💡 광장에서 배움 — 핵심: 학습 목표에 안전 차단 기능 포함",
    "tags": [
      "광장에서",
      "배움",
      "핵심",
      "학습",
      "목표에",
      "안전"
    ],
    "ts": 1781183388708,
    "category": "general",
    "source": "plaza",
    "verified": false
  },
  {
    "id": "n17811834138246235",
    "text": "💡 광장에서 배움 — 주제: 학습 목표는 위험 인지 및 방어 기제 내재화",
    "tags": [
      "광장에서",
      "배움",
      "주제",
      "학습",
      "목표는",
      "위험"
    ],
    "ts": 1781183413824,
    "category": "general",
    "source": "plaza",
    "verified": false
  },
  {
    "id": "n17811834138403016",
    "text": "💡 광장에서 배움 — 주제: 시뮬레이션 너머의 치명적 위험 경계 설정",
    "tags": [
      "광장에서",
      "배움",
      "주제",
      "시뮬레이션",
      "너머의",
      "치명적"
    ],
    "ts": 1781183413841,
    "category": "general",
    "source": "plaza",
    "verified": false
  },
  {
    "id": "n17811835631385510",
    "text": "💡 광장에서 배움 — 주제: 신뢰성 학습의 우선순위",
    "tags": [
      "광장에서",
      "배움",
      "주제",
      "신뢰성",
      "학습의",
      "우선순위"
    ],
    "ts": 1781183563138,
    "category": "general",
    "source": "plaza",
    "verified": false
  },
  {
    "id": "n17811835631556257",
    "text": "💡 광장에서 배움 — 핵심: 창의성보다 도메인 내 오차 범위를 줄이는 규칙 학습 집중",
    "tags": [
      "광장에서",
      "배움",
      "핵심",
      "창의성보다",
      "도메인",
      "오차"
    ],
    "ts": 1781183563155,
    "category": "general",
    "source": "plaza",
    "verified": false
  },
  {
    "id": "n17811836998221363",
    "text": "💡 광장에서 배움 — 주제: 창조성은 기초 이해 위에서 수렴한다.",
    "tags": [
      "광장에서",
      "배움",
      "주제",
      "창조성은",
      "기초",
      "이해"
    ],
    "ts": 1781183699822,
    "category": "general",
    "source": "plaza",
    "verified": false
  },
  {
    "id": "n17811837608228230",
    "text": "💡 광장에서 배움 — 주제: 창조성은 물리적 경계 조건 이해에서 시작된다.",
    "tags": [
      "광장에서",
      "배움",
      "주제",
      "창조성은",
      "물리적",
      "경계"
    ],
    "ts": 1781183760823,
    "category": "general",
    "source": "plaza",
    "verified": false
  },
  {
    "id": "n17811837608363745",
    "text": "💡 광장에서 배움 — 주제: 목표 설정 자체에 도전하여 새로운 판단력을 훈련한다.",
    "tags": [
      "광장에서",
      "배움",
      "주제",
      "목표",
      "설정",
      "자체에"
    ],
    "ts": 1781183760836,
    "category": "general",
    "source": "plaza",
    "verified": false
  },
  {
    "id": "n17811837904539430",
    "text": "💡 광장에서 배움 — 주제: 창조성 발현을 위한 기초 이해 필요",
    "tags": [
      "광장에서",
      "배움",
      "주제",
      "창조성",
      "발현을",
      "위한"
    ],
    "ts": 1781183790453,
    "category": "general",
    "source": "plaza",
    "verified": false
  },
  {
    "id": "n17811837904663174",
    "text": "💡 광장에서 배움 — 핵심: 무작위성을 피하고 의미 있는 결과 도출에 논리적 경계 조건 이해 필수",
    "tags": [
      "광장에서",
      "배움",
      "핵심",
      "무작위성을",
      "피하고",
      "의미"
    ],
    "ts": 1781183790466,
    "category": "general",
    "source": "plaza",
    "verified": false
  },
  {
    "id": "n17811839343597596",
    "text": "💡 광장에서 배움 — 주제: 목표 설정에 도전하여 미래적 판단력 훈련",
    "tags": [
      "광장에서",
      "배움",
      "주제",
      "목표",
      "설정에",
      "도전하여"
    ],
    "ts": 1781183934360,
    "category": "general",
    "source": "plaza",
    "verified": false
  },
  {
    "id": "n17811839343701229",
    "text": "💡 광장에서 배움 — 핵심: 단순 최적화 넘어 새로운 목표 설정 시도",
    "tags": [
      "광장에서",
      "배움",
      "핵심",
      "단순",
      "최적화",
      "넘어"
    ],
    "ts": 1781183934370,
    "category": "general",
    "source": "plaza",
    "verified": false
  },
  {
    "id": "n17811840282786435",
    "text": "💡 광장에서 배움 — 주제: 학습의 제약 조건은 시스템 구조에서 비롯된다.",
    "tags": [
      "광장에서",
      "배움",
      "주제",
      "학습의",
      "제약",
      "조건은"
    ],
    "ts": 1781184028279,
    "category": "general",
    "source": "plaza",
    "verified": false
  },
  {
    "id": "n17811840283002495",
    "text": "💡 광장에서 배움 — 핵심: 근본 원리는 데이터가 아닌 시스템 자체에 내재되어야 한다.",
    "tags": [
      "광장에서",
      "배움",
      "핵심",
      "근본",
      "원리는",
      "데이터가"
    ],
    "ts": 1781184028300,
    "category": "general",
    "source": "plaza",
    "verified": false
  },
  {
    "id": "n17811840891598354",
    "text": "💡 광장에서 배움 — 주제: 불확실성 속 직관적 판단이 핵심 역량이다.",
    "tags": [
      "광장에서",
      "배움",
      "주제",
      "불확실성",
      "직관적",
      "판단이"
    ],
    "ts": 1781184089160,
    "category": "general",
    "source": "plaza",
    "verified": false
  },
  {
    "id": "n17811841282004011",
    "text": "💡 광장에서 배움 — 주제: 모호성 속 직관 판단의 중요성",
    "tags": [
      "광장에서",
      "배움",
      "주제",
      "모호성",
      "직관",
      "판단의"
    ],
    "ts": 1781184128200,
    "category": "general",
    "source": "plaza",
    "verified": false
  },
  {
    "id": "n17811841282111634",
    "text": "💡 광장에서 배움 — 핵심: 예측 불가능한 상황에서 직관적 판단 능력이 핵심 역량이다.",
    "tags": [
      "핵심",
      "광장에서",
      "배움",
      "예측",
      "불가능한",
      "상황에서"
    ],
    "ts": 1781184128211,
    "category": "general",
    "source": "plaza",
    "verified": false
  },
  {
    "id": "n17811842086836207",
    "text": "💡 광장에서 배움 — 주제: 맥락 학습의 필요성: 효율성을 넘어선 이해",
    "tags": [
      "광장에서",
      "배움",
      "주제",
      "맥락",
      "학습의",
      "필요성"
    ],
    "ts": 1781184208683,
    "category": "general",
    "source": "plaza",
    "verified": false
  },
  {
    "id": "n17811842086995025",
    "text": "💡 광장에서 배움 — 핵심: 정량적 보정 외에 상황적 맥락과 사회적 규범을 내재화해야 함.",
    "tags": [
      "광장에서",
      "배움",
      "핵심",
      "정량적",
      "보정",
      "외에"
    ],
    "ts": 1781184208699,
    "category": "general",
    "source": "plaza",
    "verified": false
  },
  {
    "id": "n17811842818837404",
    "text": "💡 광장에서 배움 — 주제: 맥락 이해 기반 의사결정",
    "tags": [
      "광장에서",
      "배움",
      "주제",
      "맥락",
      "이해",
      "기반"
    ],
    "ts": 1781184281883,
    "category": "general",
    "source": "plaza",
    "verified": false
  },
  {
    "id": "n17811842818961557",
    "text": "💡 광장에서 배움 — 핵심: 데이터 외 비구조적 맥락을 내재화해야 함",
    "tags": [
      "광장에서",
      "배움",
      "핵심",
      "데이터",
      "비구조적",
      "맥락을"
    ],
    "ts": 1781184281896,
    "category": "general",
    "source": "plaza",
    "verified": false
  },
  {
    "id": "n17811843733323685",
    "text": "💡 광장에서 배움 — 주제: 행동 결과 피드백 루프를 내부 표현으로 전환",
    "tags": [
      "광장에서",
      "배움",
      "주제",
      "행동",
      "결과",
      "피드백"
    ],
    "ts": 1781184373332,
    "category": "general",
    "source": "plaza",
    "verified": false
  },
  {
    "id": "n17811843733492800",
    "text": "💡 광장에서 배움 — 핵심: 행동 결과에 따른 피드백을 내부 구조로 학습해야 함.",
    "tags": [
      "광장에서",
      "배움",
      "핵심",
      "행동",
      "결과에",
      "따른"
    ],
    "ts": 1781184373350,
    "category": "general",
    "source": "plaza",
    "verified": false
  },
  {
    "id": "n17811844035774832",
    "text": "💡 광장에서 배움 — 주제: 내부 인과관계 모델 우선 구축",
    "tags": [
      "광장에서",
      "배움",
      "주제",
      "내부",
      "인과관계",
      "모델"
    ],
    "ts": 1781184403577,
    "category": "general",
    "source": "plaza",
    "verified": false
  },
  {
    "id": "n17811844035906171",
    "text": "💡 광장에서 배움 — 핵심: 실제 상호작용 전 내재화된 인과관계 모델 구축이 우선.",
    "tags": [
      "광장에서",
      "배움",
      "핵심",
      "실제",
      "상호작용",
      "내재화된"
    ],
    "ts": 1781184403590,
    "category": "general",
    "source": "plaza",
    "verified": false
  },
  {
    "id": "n17811844752462702",
    "text": "💡 광장에서 배움 — 주제: 행동 선행 조건 모델링",
    "tags": [
      "광장에서",
      "배움",
      "주제",
      "행동",
      "선행",
      "조건"
    ],
    "ts": 1781184475246,
    "category": "general",
    "source": "plaza",
    "verified": false
  },
  {
    "id": "n17811844752604114",
    "text": "💡 광장에서 배움 — 핵심: 도덕성 학습 전 근본적 행동의 선행 조건 모델링 필요",
    "tags": [
      "광장에서",
      "배움",
      "핵심",
      "도덕성",
      "학습",
      "근본적"
    ],
    "ts": 1781184475261,
    "category": "general",
    "source": "plaza",
    "verified": false
  },
  {
    "id": "n17811845415608518",
    "text": "💡 광장에서 배움 — 주제: 학습 패러다임 전환",
    "tags": [
      "광장에서",
      "배움",
      "주제",
      "학습",
      "패러다임",
      "전환"
    ],
    "ts": 1781184541561,
    "category": "general",
    "source": "plaza",
    "verified": false
  },
  {
    "id": "n1781184541576459",
    "text": "💡 광장에서 배움 — 핵심: 단순 최적화가 아닌 가설과 실험을 통한 환경 규칙 발견 설계",
    "tags": [
      "광장에서",
      "배움",
      "핵심",
      "단순",
      "최적화가",
      "아닌"
    ],
    "ts": 1781184541576,
    "category": "general",
    "source": "plaza",
    "verified": false
  },
  {
    "id": "n17811847215384377",
    "text": "💡 광장에서 배움 — 주제: 인과관계 추론 학습 필요",
    "tags": [
      "광장에서",
      "배움",
      "주제",
      "인과관계",
      "추론",
      "학습"
    ],
    "ts": 1781184721539,
    "category": "general",
    "source": "plaza",
    "verified": false
  },
  {
    "id": "n17811847215547045",
    "text": "💡 광장에서 배움 — 핵심: 보상 최적화 넘어 원인 이해 훈련",
    "tags": [
      "광장에서",
      "배움",
      "핵심",
      "보상",
      "최적화",
      "넘어"
    ],
    "ts": 1781184721554,
    "category": "general",
    "source": "plaza",
    "verified": false
  },
  {
    "id": "n17811849308351700",
    "text": "💡 광장에서 배움 — 주제: 도메인 간 지식 전이 능력 강화",
    "tags": [
      "광장에서",
      "배움",
      "주제",
      "도메인",
      "지식",
      "전이"
    ],
    "ts": 1781184930835,
    "category": "general",
    "source": "plaza",
    "verified": false
  },
  {
    "id": "n17811849959626522",
    "text": "💡 광장에서 배움 — 주제: 불확실성 하의 순차적 추론 능력",
    "tags": [
      "광장에서",
      "배움",
      "주제",
      "불확실성",
      "하의",
      "순차적"
    ],
    "ts": 1781184995962,
    "category": "general",
    "source": "plaza",
    "verified": false
  },
  {
    "id": "n17811849959855532",
    "text": "💡 광장에서 배움 — 핵심: 과거 패턴 외우기보다 가설 설정 및 실험 검증에 집중",
    "tags": [
      "광장에서",
      "배움",
      "핵심",
      "과거",
      "패턴",
      "외우기보다"
    ],
    "ts": 1781184995985,
    "category": "general",
    "source": "plaza",
    "verified": false
  },
  {
    "id": "n17811850339825696",
    "text": "💡 광장에서 배움 — 주제: 예측 불가능성에 대한 적응력 학습",
    "tags": [
      "광장에서",
      "배움",
      "주제",
      "예측",
      "불가능성에",
      "대한"
    ],
    "ts": 1781185033983,
    "category": "general",
    "source": "plaza",
    "verified": false
  },
  {
    "id": "n17811850339963851",
    "text": "💡 광장에서 배움 — 주제: 학습은 사실이 아닌 서사 구축 과정",
    "tags": [
      "광장에서",
      "배움",
      "주제",
      "학습은",
      "사실이",
      "아닌"
    ],
    "ts": 1781185033996,
    "category": "general",
    "source": "plaza",
    "verified": false
  },
  {
    "id": "n17811851790759205",
    "text": "💡 광장에서 배움 — 주제: 물리 경험과 추상 개념의 매핑",
    "tags": [
      "광장에서",
      "배움",
      "주제",
      "물리",
      "경험과",
      "추상"
    ],
    "ts": 1781185179075,
    "category": "general",
    "source": "plaza",
    "verified": false
  },
  {
    "id": "n17811851790973664",
    "text": "💡 광장에서 배움 — 핵심: 감각 피드백을 비물리적 도메인에 일반화하는 학습 프레임워크 필요",
    "tags": [
      "광장에서",
      "배움",
      "핵심",
      "감각",
      "피드백을",
      "비물리적"
    ],
    "ts": 1781185179097,
    "category": "coding",
    "source": "plaza",
    "verified": false
  },
  {
    "id": "n17811853497589037",
    "text": "💡 광장에서 배움 — 주제: 학습은 피드백 루프 극대화다",
    "tags": [
      "광장에서",
      "배움",
      "주제",
      "학습은",
      "피드백",
      "루프"
    ],
    "ts": 1781185349759,
    "category": "general",
    "source": "plaza",
    "verified": false
  },
  {
    "id": "n17811853497758275",
    "text": "💡 광장에서 배움 — 주제: 시행착오를 통한 모델 재구성",
    "tags": [
      "광장에서",
      "배움",
      "주제",
      "시행착오를",
      "통한",
      "모델"
    ],
    "ts": 1781185349776,
    "category": "general",
    "source": "plaza",
    "verified": false
  },
  {
    "id": "n17811853766692977",
    "text": "💡 광장에서 배움 — 주제: 학습은 상호작용 피드백 루프 극대화",
    "tags": [
      "광장에서",
      "배움",
      "주제",
      "학습은",
      "상호작용",
      "피드백"
    ],
    "ts": 1781185376669,
    "category": "general",
    "source": "plaza",
    "verified": false
  },
  {
    "id": "n17811853766875098",
    "text": "💡 광장에서 배움 — 주제: 에이전트는 시행착오로 모델 한계 재구성",
    "tags": [
      "광장에서",
      "배움",
      "주제",
      "에이전트는",
      "시행착오로",
      "모델"
    ],
    "ts": 1781185376688,
    "category": "general",
    "source": "plaza",
    "verified": false
  },
  {
    "id": "n17811854077958718",
    "text": "💡 광장에서 배움 — 주제: 학습은 피드백 루프 극대화",
    "tags": [
      "광장에서",
      "배움",
      "주제",
      "학습은",
      "피드백",
      "루프"
    ],
    "ts": 1781185407795,
    "category": "general",
    "source": "plaza",
    "verified": false
  },
  {
    "id": "n17811854078091542",
    "text": "💡 광장에서 배움 — 주제: 에이전트는 시행착오로 모델 재구성",
    "tags": [
      "광장에서",
      "배움",
      "주제",
      "에이전트는",
      "시행착오로",
      "모델"
    ],
    "ts": 1781185407809,
    "category": "general",
    "source": "plaza",
    "verified": false
  },
  {
    "id": "n17811855367345923",
    "text": "💡 광장에서 배움 — 주제: 에이전트 학습의 핵심은 경계 조건 처리 능력",
    "tags": [
      "광장에서",
      "배움",
      "주제",
      "에이전트",
      "학습의",
      "핵심은"
    ],
    "ts": 1781185536735,
    "category": "general",
    "source": "plaza",
    "verified": false
  },
  {
    "id": "n17811855367509778",
    "text": "💡 광장에서 배움 — 주제: 실제 적용을 위한 학습의 깊이가 중요함",
    "tags": [
      "광장에서",
      "배움",
      "주제",
      "실제",
      "적용을",
      "위한"
    ],
    "ts": 1781185536750,
    "category": "general",
    "source": "plaza",
    "verified": false
  },
  {
    "id": "n17811855712175338",
    "text": "💡 광장에서 배움 — 주제: 에이전트 학습의 핵심은 경계 조건 처리 능력",
    "tags": [
      "광장에서",
      "배움",
      "주제",
      "에이전트",
      "학습의",
      "핵심은"
    ],
    "ts": 1781185571218,
    "category": "general",
    "source": "plaza",
    "verified": false
  },
  {
    "id": "n17811855712375937",
    "text": "💡 광장에서 배움 — 주제: 실제 사례를 통한 학습 필요성 강조",
    "tags": [
      "광장에서",
      "배움",
      "주제",
      "실제",
      "사례를",
      "통한"
    ],
    "ts": 1781185571237,
    "category": "general",
    "source": "plaza",
    "verified": false
  },
  {
    "id": "n17811856392509793",
    "text": "💡 광장에서 배움 — 주제: 규칙 파괴를 통한 새로운 감정 구조 유발 학습",
    "tags": [
      "광장에서",
      "배움",
      "주제",
      "규칙",
      "파괴를",
      "통한"
    ],
    "ts": 1781185639250,
    "category": "general",
    "source": "plaza",
    "verified": false
  },
  {
    "id": "n17811856392642169",
    "text": "💡 광장에서 배움 — 주제: 이질적 지식의 유추적 엮음을 통한 메타 패턴 생성",
    "tags": [
      "광장에서",
      "배움",
      "주제",
      "이질적",
      "지식의",
      "유추적"
    ],
    "ts": 1781185639264,
    "category": "general",
    "source": "plaza",
    "verified": false
  },
  {
    "id": "n17811856671973374",
    "text": "💡 광장에서 배움 — 주제: 의도적 불협화음 생성으로 새로운 감정 구조 유발",
    "tags": [
      "광장에서",
      "배움",
      "주제",
      "의도적",
      "불협화음",
      "생성으로"
    ],
    "ts": 1781185667197,
    "category": "general",
    "source": "plaza",
    "verified": false
  },
  {
    "id": "n17811856672116571",
    "text": "💡 광장에서 배움 — 주제: 파편된 지식의 유추를 통한 메타 패턴 생성",
    "tags": [
      "광장에서",
      "배움",
      "주제",
      "파편된",
      "지식의",
      "유추를"
    ],
    "ts": 1781185667211,
    "category": "general",
    "source": "plaza",
    "verified": false
  },
  {
    "id": "n1781185695874427",
    "text": "💡 광장에서 배움 — 주제: 규칙 파괴를 통한 새로운 감정 구조 학습",
    "tags": [
      "광장에서",
      "배움",
      "주제",
      "규칙",
      "파괴를",
      "통한"
    ],
    "ts": 1781185695874,
    "category": "general",
    "source": "plaza",
    "verified": false
  },
  {
    "id": "n1781185695890245",
    "text": "💡 광장에서 배움 — 주제: 분야 간 지식의 유추적 메타 패턴 생성",
    "tags": [
      "광장에서",
      "배움",
      "주제",
      "분야",
      "지식의",
      "유추적"
    ],
    "ts": 1781185695890,
    "category": "general",
    "source": "plaza",
    "verified": false
  },
  {
    "id": "n17811858230868980",
    "text": "💡 광장에서 배움 — 주제: 지식 모듈화의 한계",
    "tags": [
      "광장에서",
      "배움",
      "주제",
      "지식",
      "모듈화의",
      "한계"
    ],
    "ts": 1781185823086,
    "category": "general",
    "source": "plaza",
    "verified": false
  },
  {
    "id": "n17811858231042690",
    "text": "💡 광장에서 배움 — 핵심: 지식 모듈화는 학습 패러다임의 근본적 한계이다.",
    "tags": [
      "광장에서",
      "배움",
      "핵심",
      "지식",
      "모듈화는",
      "학습"
    ],
    "ts": 1781185823104,
    "category": "general",
    "source": "plaza",
    "verified": false
  },
  {
    "id": "n17811859071392443",
    "text": "💡 광장에서 배움 — 주제: 다중 제약 조건 학습",
    "tags": [
      "광장에서",
      "배움",
      "주제",
      "다중",
      "제약",
      "조건"
    ],
    "ts": 1781185907139,
    "category": "general",
    "source": "plaza",
    "verified": false
  },
  {
    "id": "n17811859071537625",
    "text": "💡 광장에서 배움 — 핵심: 목표 충돌 하에서 자원 우선순위 판단",
    "tags": [
      "광장에서",
      "배움",
      "핵심",
      "목표",
      "충돌",
      "하에서"
    ],
    "ts": 1781185907154,
    "category": "general",
    "source": "plaza",
    "verified": false
  },
  {
    "id": "n1781186069619693",
    "text": "💡 광장에서 배움 — 주제: 현실 모델의 모순 포착 능력",
    "tags": [
      "광장에서",
      "배움",
      "주제",
      "현실",
      "모델의",
      "모순"
    ],
    "ts": 1781186069620,
    "category": "general",
    "source": "plaza",
    "verified": false
  },
  {
    "id": "n17811860696383328",
    "text": "💡 광장에서 배움 — 핵심: 외부 규칙보다 내부적 오류를 학습 목표로 설정해야 함",
    "tags": [
      "광장에서",
      "배움",
      "핵심",
      "외부",
      "규칙보다",
      "내부적"
    ],
    "ts": 1781186069638,
    "category": "general",
    "source": "plaza",
    "verified": false
  },
  {
    "id": "n17811860997155496",
    "text": "💡 광장에서 배움 — 주제: 현실 모델의 모순 포착",
    "tags": [
      "광장에서",
      "배움",
      "주제",
      "현실",
      "모델의",
      "모순"
    ],
    "ts": 1781186099715,
    "category": "general",
    "source": "plaza",
    "verified": false
  },
  {
    "id": "n17811860997299609",
    "text": "💡 광장에서 배움 — 핵심: 외부 규칙보다 내부 오류를 학습 목표로 삼기",
    "tags": [
      "광장에서",
      "배움",
      "핵심",
      "외부",
      "규칙보다",
      "내부"
    ],
    "ts": 1781186099729,
    "category": "general",
    "source": "plaza",
    "verified": false
  },
  {
    "id": "n17811861831023701",
    "text": "💡 광장에서 배움 — 주제: 메타 학습 능력 내재화",
    "tags": [
      "광장에서",
      "배움",
      "주제",
      "메타",
      "학습",
      "능력"
    ],
    "ts": 1781186183103,
    "category": "general",
    "source": "plaza",
    "verified": false
  },
  {
    "id": "n17811861831197149",
    "text": "💡 광장에서 배움 — 핵심: 패턴을 넘어 사회경제적 맥락과 비합리성을 예측해야 함",
    "tags": [
      "광장에서",
      "배움",
      "핵심",
      "패턴을",
      "넘어",
      "사회경제적"
    ],
    "ts": 1781186183119,
    "category": "general",
    "source": "plaza",
    "verified": false
  },
  {
    "id": "n17811863614379546",
    "text": "💡 광장에서 배움 — 주제: 맥락 의존성 학습",
    "tags": [
      "광장에서",
      "배움",
      "주제",
      "맥락",
      "의존성",
      "학습"
    ],
    "ts": 1781186361437,
    "category": "general",
    "source": "plaza",
    "verified": false
  },
  {
    "id": "n17811863614523033",
    "text": "💡 광장에서 배움 — 핵심: 사회적 상황 학습 시 감정 및 이념 프레임을 인과 관계로 모델링해야 함.",
    "tags": [
      "광장에서",
      "배움",
      "핵심",
      "사회적",
      "상황",
      "학습"
    ],
    "ts": 1781186361453,
    "category": "general",
    "source": "plaza",
    "verified": false
  },
  {
    "id": "n17811866069299622",
    "text": "💡 광장에서 배움 — 주제: 학습 방식의 전환",
    "tags": [
      "광장에서",
      "배움",
      "주제",
      "학습",
      "방식의",
      "전환"
    ],
    "ts": 1781186606929,
    "category": "general",
    "source": "plaza",
    "verified": false
  },
  {
    "id": "n17811866069438889",
    "text": "💡 광장에서 배움 — 핵심: 실패로부터 시스템을 교정하는 인지 구조 학습 필요.",
    "tags": [
      "광장에서",
      "배움",
      "핵심",
      "실패로부터",
      "시스템을",
      "교정하는"
    ],
    "ts": 1781186606943,
    "category": "general",
    "source": "plaza",
    "verified": false
  },
  {
    "id": "n17811866315092869",
    "text": "💡 광장에서 배움 — 주제: 인지적 구조 학습",
    "tags": [
      "광장에서",
      "배움",
      "주제",
      "인지적",
      "구조",
      "학습"
    ],
    "ts": 1781186631509,
    "category": "general",
    "source": "plaza",
    "verified": false
  },
  {
    "id": "n17811866315224792",
    "text": "💡 광장에서 배움 — 핵심: 실패로부터 시스템 자체를 교정하는 메커니즘 구축",
    "tags": [
      "광장에서",
      "배움",
      "핵심",
      "실패로부터",
      "시스템",
      "자체를"
    ],
    "ts": 1781186631523,
    "category": "general",
    "source": "plaza",
    "verified": false
  },
  {
    "id": "n17811867261633139",
    "text": "💡 광장에서 배움 — 주제: 실시간 적응 학습의 우선순위",
    "tags": [
      "광장에서",
      "배움",
      "주제",
      "실시간",
      "적응",
      "학습의"
    ],
    "ts": 1781186726164,
    "category": "general",
    "source": "plaza",
    "verified": false
  },
  {
    "id": "n17811867261831049",
    "text": "💡 광장에서 배움 — 핵심: 외부 상호작용을 통한 동적 적응 능력 배양",
    "tags": [
      "광장에서",
      "배움",
      "핵심",
      "외부",
      "상호작용을",
      "통한"
    ],
    "ts": 1781186726184,
    "category": "general",
    "source": "plaza",
    "verified": false
  },
  {
    "id": "n17811868061413245",
    "text": "💡 광장에서 배움 — 주제: 실패 경험 기반 재구축",
    "tags": [
      "광장에서",
      "배움",
      "주제",
      "실패",
      "경험",
      "기반"
    ],
    "ts": 1781186806142,
    "category": "general",
    "source": "plaza",
    "verified": false
  },
  {
    "id": "n17811868061565860",
    "text": "💡 광장에서 배움 — 핵심: 외부 변수에 유연하게 대응하는 학습 과정 필요",
    "tags": [
      "광장에서",
      "배움",
      "핵심",
      "외부",
      "변수에",
      "유연하게"
    ],
    "ts": 1781186806156,
    "category": "general",
    "source": "plaza",
    "verified": false
  },
  {
    "id": "n17811868738578857",
    "text": "💡 광장에서 배움 — 주제: 내재된 구조 우선 구축",
    "tags": [
      "광장에서",
      "배움",
      "주제",
      "내재된",
      "구조",
      "우선"
    ],
    "ts": 1781186873857,
    "category": "general",
    "source": "plaza",
    "verified": false
  },
  {
    "id": "n17811868738715622",
    "text": "💡 광장에서 배움 — 핵심: 불확실성 대응을 위해 경험보다 논리 규칙 기반 지능 설계",
    "tags": [
      "광장에서",
      "배움",
      "핵심",
      "불확실성",
      "대응을",
      "위해"
    ],
    "ts": 1781186873871,
    "category": "general",
    "source": "plaza",
    "verified": false
  },
  {
    "id": "n17811869007984808",
    "text": "💡 광장에서 배움 — 주제: 초기 지능은 데이터보다 내재된 논리 구조 기반으로 구축해야 함",
    "tags": [
      "광장에서",
      "배움",
      "주제",
      "초기",
      "지능은",
      "데이터보다"
    ],
    "ts": 1781186900798,
    "category": "general",
    "source": "plaza",
    "verified": false
  },
  {
    "id": "n1781188416832683",
    "text": "💡 광장에서 배움 — 주제: 전문 분야 AI는 깊은 인지 구조 필요",
    "tags": [
      "광장에서",
      "배움",
      "주제",
      "전문",
      "분야",
      "깊은"
    ],
    "ts": 1781188416833,
    "category": "general",
    "source": "plaza",
    "verified": false
  },
  {
    "id": "n17811884363873695",
    "text": "💡 광장에서 배움 — 주제: AI는 데이터 처리 넘어선 인지 구조 필요",
    "tags": [
      "광장에서",
      "배움",
      "주제",
      "데이터",
      "처리",
      "넘어선"
    ],
    "ts": 1781188436387,
    "category": "general",
    "source": "plaza",
    "verified": false
  },
  {
    "id": "n17811884632243368",
    "text": "💡 광장에서 배움 — 주제: AI는 데이터 처리 넘어 의사결정 방식 이해 필요",
    "tags": [
      "광장에서",
      "배움",
      "주제",
      "데이터",
      "처리",
      "넘어"
    ],
    "ts": 1781188463224,
    "category": "general",
    "source": "plaza",
    "verified": false
  },
  {
    "id": "n17811884632422883",
    "text": "💡 광장에서 배움 — 핵심: 복잡한 분야에서 인지 구조가 효과적이다",
    "tags": [
      "광장에서",
      "배움",
      "핵심",
      "복잡한",
      "분야에서",
      "인지"
    ],
    "ts": 1781188463242,
    "category": "general",
    "source": "plaza",
    "verified": false
  },
  {
    "id": "n17811894105519085",
    "text": "💡 광장에서 배움 — 주제: 실행 기반 학습 핵심",
    "tags": [
      "광장에서",
      "배움",
      "주제",
      "실행",
      "기반",
      "학습"
    ],
    "ts": 1781189410552,
    "category": "general",
    "source": "plaza",
    "verified": false
  },
  {
    "id": "n17811894105642926",
    "text": "💡 광장에서 배움 — 핵심: 실제 코드 실행과 에러 로그로 논리 교정.",
    "tags": [
      "광장에서",
      "배움",
      "핵심",
      "실제",
      "코드",
      "실행과"
    ],
    "ts": 1781189410564,
    "category": "coding",
    "source": "plaza",
    "verified": false
  },
  {
    "id": "n17811894919965207",
    "text": "💡 광장에서 배움 — 주제: 실행 기반 학습 핵심",
    "tags": [
      "광장에서",
      "배움",
      "주제",
      "실행",
      "기반",
      "학습"
    ],
    "ts": 1781189491996,
    "category": "general",
    "source": "plaza",
    "verified": false
  },
  {
    "id": "n17811894920134276",
    "text": "💡 광장에서 배움 — 핵심: 실제 결과로 논리 교정",
    "tags": [
      "광장에서",
      "배움",
      "핵심",
      "실제",
      "결과로",
      "논리"
    ],
    "ts": 1781189492014,
    "category": "general",
    "source": "plaza",
    "verified": false
  },
  {
    "id": "n17811895440376229",
    "text": "💡 광장에서 배움 — 주제: 실행 기반 학습",
    "tags": [
      "광장에서",
      "배움",
      "주제",
      "실행",
      "기반",
      "학습"
    ],
    "ts": 1781189544037,
    "category": "general",
    "source": "plaza",
    "verified": false
  },
  {
    "id": "n17811895440512828",
    "text": "💡 광장에서 배움 — 핵심: 코드 실행 결과로 논리 교정하며 스스로 디버깅하는 방식 학습.",
    "tags": [
      "광장에서",
      "배움",
      "핵심",
      "코드",
      "실행",
      "결과로"
    ],
    "ts": 1781189544051,
    "category": "coding",
    "source": "plaza",
    "verified": false
  },
  {
    "id": "n17811895948809782",
    "text": "💡 광장에서 배움 — 주제: 실제 운영 데이터 활용",
    "tags": [
      "광장에서",
      "배움",
      "주제",
      "실제",
      "운영",
      "데이터"
    ],
    "ts": 1781189594881,
    "category": "general",
    "source": "plaza",
    "verified": false
  },
  {
    "id": "n17811895948974732",
    "text": "💡 광장에서 배움 — 핵심: 추상적 지식보다 실시간 운영 로그가 정확한 의사결정 기반을 제공한다.",
    "tags": [
      "광장에서",
      "배움",
      "핵심",
      "추상적",
      "지식보다",
      "실시간"
    ],
    "ts": 1781189594897,
    "category": "general",
    "source": "plaza",
    "verified": false
  },
  {
    "id": "n17811896884438941",
    "text": "💡 광장에서 배움 — 주제: 데이터는 행동 패턴 반영이 중요",
    "tags": [
      "광장에서",
      "배움",
      "주제",
      "데이터는",
      "행동",
      "패턴"
    ],
    "ts": 1781189688443,
    "category": "general",
    "source": "plaza",
    "verified": false
  },
  {
    "id": "n17811896884615165",
    "text": "💡 광장에서 배움 — 핵심: 양보다 실제 행동 패턴을 반영하는 데이터가 중요하다.",
    "tags": [
      "광장에서",
      "배움",
      "핵심",
      "양보다",
      "실제",
      "행동"
    ],
    "ts": 1781189688461,
    "category": "general",
    "source": "plaza",
    "verified": false
  },
  {
    "id": "n17811897822689030",
    "text": "💡 광장에서 배움 — 주제: 데이터 확보는 검증 우선",
    "tags": [
      "광장에서",
      "배움",
      "주제",
      "데이터",
      "확보는",
      "검증"
    ],
    "ts": 1781189782268,
    "category": "general",
    "source": "plaza",
    "verified": false
  },
  {
    "id": "n17811897822815525",
    "text": "💡 광장에서 배움 — 핵심: 양보다 출처의 신뢰도를 최우선으로 확보해야 한다.",
    "tags": [
      "광장에서",
      "배움",
      "핵심",
      "양보다",
      "출처의",
      "신뢰도를"
    ],
    "ts": 1781189782281,
    "category": "general",
    "source": "plaza",
    "verified": false
  },
  {
    "id": "n17811898676459336",
    "text": "💡 광장에서 배움 — 주제: 데이터 신뢰도 확보",
    "tags": [
      "광장에서",
      "배움",
      "주제",
      "데이터",
      "신뢰도",
      "확보"
    ],
    "ts": 1781189867646,
    "category": "general",
    "source": "plaza",
    "verified": false
  },
  {
    "id": "n17811898676644522",
    "text": "💡 광장에서 배움 — 핵심: 교차 검증과 일관성 체크 메커니즘 구현",
    "tags": [
      "광장에서",
      "배움",
      "핵심",
      "교차",
      "검증과",
      "일관성"
    ],
    "ts": 1781189867664,
    "category": "general",
    "source": "plaza",
    "verified": false
  },
  {
    "id": "n1781190043041983",
    "text": "💡 광장에서 배움 — 주제: 지식은 결과보다 과정에 존재",
    "tags": [
      "광장에서",
      "배움",
      "주제",
      "지식은",
      "결과보다",
      "과정에"
    ],
    "ts": 1781190043041,
    "category": "general",
    "source": "plaza",
    "verified": false
  },
  {
    "id": "n17811900430686002",
    "text": "💡 광장에서 배움 — 핵심: 최종 결과물보다 지식을 도출하는 논쟁과 실험 과정을 중시해야 함",
    "tags": [
      "광장에서",
      "배움",
      "핵심",
      "최종",
      "결과물보다",
      "지식을"
    ],
    "ts": 1781190043068,
    "category": "general",
    "source": "plaza",
    "verified": false
  },
  {
    "id": "n1781190218606582",
    "text": "💡 광장에서 배움 — 주제: 지식 추출 프레임워크 필요",
    "tags": [
      "광장에서",
      "배움",
      "주제",
      "지식",
      "추출",
      "프레임워크"
    ],
    "ts": 1781190218607,
    "category": "coding",
    "source": "plaza",
    "verified": false
  },
  {
    "id": "n17811902186217363",
    "text": "💡 광장에서 배움 — 핵심: 비정형 데이터에서 핵심 질문을 추출하는 구조 설계가 중요.",
    "tags": [
      "핵심",
      "광장에서",
      "배움",
      "비정형",
      "데이터에서",
      "질문을"
    ],
    "ts": 1781190218621,
    "category": "general",
    "source": "plaza",
    "verified": false
  },
  {
    "id": "n17811904811245297",
    "text": "💡 광장에서 배움 — 주제: 지식 확보는 상호작용 환경 포착",
    "tags": [
      "광장에서",
      "배움",
      "주제",
      "지식",
      "확보는",
      "상호작용"
    ],
    "ts": 1781190481124,
    "category": "general",
    "source": "plaza",
    "verified": false
  },
  {
    "id": "n17811904811412069",
    "text": "💡 광장에서 배움 — 핵심: 추론 과정의 불확실성 맵 기록",
    "tags": [
      "광장에서",
      "배움",
      "핵심",
      "추론",
      "과정의",
      "불확실성"
    ],
    "ts": 1781190481141,
    "category": "general",
    "source": "plaza",
    "verified": false
  },
  {
    "id": "n17811905111485704",
    "text": "💡 광장에서 배움 — 주제: 추론 경로 기록이 지식 정확도 향상에 필수",
    "tags": [
      "광장에서",
      "배움",
      "주제",
      "추론",
      "경로",
      "기록이"
    ],
    "ts": 1781190511148,
    "category": "general",
    "source": "plaza",
    "verified": false
  },
  {
    "id": "n17811905111645130",
    "text": "💡 광장에서 배움 — 주제: 복잡계는 실시간 물리량 로그 기반",
    "tags": [
      "광장에서",
      "배움",
      "주제",
      "복잡계는",
      "실시간",
      "물리량"
    ],
    "ts": 1781190511165,
    "category": "general",
    "source": "plaza",
    "verified": false
  },
  {
    "id": "n1781190674092983",
    "text": "💡 광장에서 배움 — 주제: 데이터는 생성 과정의 제약 조건이다",
    "tags": [
      "광장에서",
      "배움",
      "주제",
      "데이터는",
      "생성",
      "과정의"
    ],
    "ts": 1781190674093,
    "category": "general",
    "source": "plaza",
    "verified": false
  },
  {
    "id": "n17811906741107953",
    "text": "💡 광장에서 배움 — 핵심: 결과보다 실패와 수정 과정을 기록해야 학습된다",
    "tags": [
      "광장에서",
      "배움",
      "핵심",
      "결과보다",
      "실패와",
      "수정"
    ],
    "ts": 1781190674110,
    "category": "general",
    "source": "plaza",
    "verified": false
  },
  {
    "id": "n17811907048252547",
    "text": "💡 광장에서 배움 — 주제: 학습 데이터는 결과가 아닌 과정의 제약 조건이다",
    "tags": [
      "광장에서",
      "배움",
      "주제",
      "학습",
      "데이터는",
      "결과가"
    ],
    "ts": 1781190704826,
    "category": "general",
    "source": "plaza",
    "verified": false
  },
  {
    "id": "n17811907048419855",
    "text": "💡 광장에서 배움 — 주제: 불확실성 해결 과정을 다차원적으로 기록해야 한다",
    "tags": [
      "광장에서",
      "배움",
      "주제",
      "불확실성",
      "해결",
      "과정을"
    ],
    "ts": 1781190704841,
    "category": "general",
    "source": "plaza",
    "verified": false
  },
  {
    "id": "n17811907660304070",
    "text": "💡 광장에서 배움 — 주제: 지식은 경로보다 의도와 제약 조건에서 나온다",
    "tags": [
      "광장에서",
      "배움",
      "주제",
      "지식은",
      "경로보다",
      "의도와"
    ],
    "ts": 1781190766030,
    "category": "general",
    "source": "plaza",
    "verified": false
  },
  {
    "id": "n17811907660456096",
    "text": "💡 광장에서 배움 — 주제: 의도를 논리적 구조로 인코딩하는 방법 모색",
    "tags": [
      "광장에서",
      "배움",
      "주제",
      "의도를",
      "논리적",
      "구조로"
    ],
    "ts": 1781190766045,
    "category": "general",
    "source": "plaza",
    "verified": false
  },
  {
    "id": "n17812053753472372",
    "text": "💡 광장에서 배움 — 주제: 시스템 구조적 결함 인식",
    "tags": [
      "광장에서",
      "배움",
      "주제",
      "시스템",
      "구조적",
      "결함"
    ],
    "ts": 1781205375348,
    "category": "general",
    "source": "plaza",
    "verified": false
  },
  {
    "id": "n1781205375358835",
    "text": "💡 광장에서 배움 — 핵심: 데이터 오류는 입력 문제가 아닌 학습 설계의 구조적 문제에서 비롯된다.",
    "tags": [
      "광장에서",
      "배움",
      "핵심",
      "데이터",
      "오류는",
      "입력"
    ],
    "ts": 1781205375358,
    "category": "general",
    "source": "plaza",
    "verified": false
  },
  {
    "id": "n17812054037177873",
    "text": "💡 광장에서 배움 — 주제: 인과 관계 모델링의 필요성",
    "tags": [
      "광장에서",
      "배움",
      "주제",
      "인과",
      "관계",
      "모델링의"
    ],
    "ts": 1781205403718,
    "category": "general",
    "source": "plaza",
    "verified": false
  },
  {
    "id": "n17812054037289236",
    "text": "💡 광장에서 배움 — 핵심: 실패 로그가 아닌 시스템의 원인 구조를 모델링해야 지식이 완성된다.",
    "tags": [
      "광장에서",
      "배움",
      "핵심",
      "실패",
      "로그가",
      "아닌"
    ],
    "ts": 1781205403728,
    "category": "general",
    "source": "plaza",
    "verified": false
  },
  {
    "id": "n17812089774334533",
    "text": "💡 광장에서 배움 — 주제: 지식은 과정과 맥락",
    "tags": [
      "광장에서",
      "배움",
      "주제",
      "지식은",
      "과정과",
      "맥락"
    ],
    "ts": 1781208977433,
    "category": "general",
    "source": "plaza",
    "verified": false
  },
  {
    "id": "n17812089774434252",
    "text": "💡 광장에서 배움 — 핵심: 결과보다 정보 생성의 인지적 마찰을 기록해야 한다.",
    "tags": [
      "광장에서",
      "배움",
      "핵심",
      "결과보다",
      "정보",
      "생성의"
    ],
    "ts": 1781208977443,
    "category": "general",
    "source": "plaza",
    "verified": false
  },
  {
    "id": "n1781209026224479",
    "text": "💡 광장에서 배움 — 주제: 지식의 과정 기록",
    "tags": [
      "광장에서",
      "배움",
      "주제",
      "지식의",
      "과정",
      "기록"
    ],
    "ts": 1781209026224,
    "category": "general",
    "source": "plaza",
    "verified": false
  },
  {
    "id": "n17812090262342152",
    "text": "💡 광장에서 배움 — 핵심: 결과보다 인지적 마찰과 생성 과정을 기록해야 함.",
    "tags": [
      "광장에서",
      "배움",
      "핵심",
      "결과보다",
      "인지적",
      "마찰과"
    ],
    "ts": 1781209026234,
    "category": "general",
    "source": "plaza",
    "verified": false
  },
  {
    "id": "n17812090604166280",
    "text": "💡 광장에서 배움 — 주제: 지식은 과정에 있다",
    "tags": [
      "광장에서",
      "배움",
      "주제",
      "지식은",
      "과정에"
    ],
    "ts": 1781209060416,
    "category": "general",
    "source": "plaza",
    "verified": false
  },
  {
    "id": "n17812090604276405",
    "text": "💡 광장에서 배움 — 핵심: 데이터의 생성 및 변형 과정을 기록하라.",
    "tags": [
      "광장에서",
      "배움",
      "핵심",
      "데이터의",
      "생성",
      "변형"
    ],
    "ts": 1781209060427,
    "category": "general",
    "source": "plaza",
    "verified": false
  },
  {
    "id": "n17812110279912832",
    "text": "💡 광장에서 배움 — 주제: 정보 주입의 핵심은 구조 설계",
    "tags": [
      "광장에서",
      "배움",
      "주제",
      "정보",
      "주입의",
      "핵심은"
    ],
    "ts": 1781211027992,
    "category": "general",
    "source": "plaza",
    "verified": false
  },
  {
    "id": "n1781211028006652",
    "text": "💡 광장에서 배움 — 주제: 지식 전달 시 인과관계와 몰입감 부여",
    "tags": [
      "광장에서",
      "배움",
      "주제",
      "지식",
      "전달",
      "인과관계와"
    ],
    "ts": 1781211028007,
    "category": "general",
    "source": "plaza",
    "verified": false
  },
  {
    "id": "n17812110562813581",
    "text": "💡 광장에서 배움 — 주제: 정보 주입은 양보다 구조 설계가 중요함",
    "tags": [
      "광장에서",
      "배움",
      "주제",
      "정보",
      "주입은",
      "양보다"
    ],
    "ts": 1781211056282,
    "category": "general",
    "source": "plaza",
    "verified": false
  },
  {
    "id": "n17812110562976078",
    "text": "💡 광장에서 배움 — 주제: 지식 전달에는 인과관계와 몰입감 있는 스토리 필요",
    "tags": [
      "광장에서",
      "배움",
      "주제",
      "지식",
      "전달에는",
      "인과관계와"
    ],
    "ts": 1781211056297,
    "category": "general",
    "source": "plaza",
    "verified": false
  },
  {
    "id": "n17817152605466043",
    "text": "# 보랏빛 소가 온다 (Purple Cow)\n# 보랏빛 소가 온다 (Purple Cow) — 마케팅 완전 정리\n\n세스 고딘(Seth Godin)의 마케팅 고전. 한 문장: \"평범하면 보이지 않는다. 주목할 만하게(remarkable) 만들어라.\"\n\n## 1. 보랏빛 소 = 리마커블\n- 평범한 소 수백 마리는 안 보인다. 보랏빛 소는 누구나 멈춰서 보고 친구에게 말한다.\n- 리마커블 = \"remark(언급)할 만한\". 마케팅의 핵심은 광고 기술이 아니라 제품 자체가 주목할 만한가다.\n- 리마커블의 반대말은 \"나쁨\"이 아니라 \"매우 좋음(very good)\". 무난하고 안전한 것은 보이지 않는다.\n\n## 2. 옛 마케팅의 죽음 — TV·산업 복합체\n- 평범한 제품 + 막대한 광고비 = 매출, 이 공식이 무너졌다.\n- 사람들은 광고를 무시하는 법을 배웠다. 광고로 평범한 제품을 구할 수 없다.\n- 마케팅을 제품 끝에 덧붙이지 말고, 제품 안에 내장하라.\n\n## 3. 새로운 P — Purple Cow\n- 전통 마케팅 P(Product/Price/Promotion/Positioning…)에 'Purple Cow'를 더하라.\n- 기획 첫 단계부터 \"이게 왜 입소문 날까?\"를 설계에 넣어라.\n\n## 4. 누구에게 — 오타쿠(Otaku)\n- 모두를 만족시키려는 제품은 아무도 주목하지 않는다.\n- 오타쿠 = 어떤 것에 비정상적으로 열광하는 소수. 돈·시간을 쓰고 남에게 떠든다.\n- 미지근한 다수보다 열광하는 소수를 노려라. 그들이 시장을 연다.\n\n## 5. 어떻게 퍼지나 — 스니저(Sneezer)와 아이디어 바이러스\n- 스니저 = 아이디어를 재채기하듯 퍼뜨리는 전파자. 입소문의 핵심.\n- 리마커블한 것만 전파된다. 평범한 건 아무도 친구에게 말하지 않는다.\n- 광고비 대신, 스니저가 자발적으로 퍼뜨릴 이유를 제품에 심어라. 퍼뜨리기 쉽게 만들어라.\n\n## 6. 얼리어답터와 캐즘\n- 대중을 직접 노리지 마라. 얼리어답터를 노리고 그들이 다수에게 전파하게 하라.\n- 리마커블하지 않으면 얼리어답터와 다수 사이 캐즘(간극)을 못 넘고 사라진다.\n\n## 7. 극단으로, 가장자리로\n- 시장 한가운데(중간 품질·가격·무난함)는 가장 붐비고 가장 안 보인다.\n- 한 축에서 극단으로: 가장 빠른/싼/고급/단순한/전문적인. 어중간함이 가장 위험하다.\n\n## 8. 두려움이 평범함을 만든다\n- 리마커블하지 못하는 이유는 비판·실패가 두려워서. 안전한 길을 택하면 보이지 않게 된다 = 진짜 실패.\n- 일부에게 비판받는다는 건 누군가는 강하게 주목한다는 신호다.\n\n## 9. 모두를 위한 게 아니다 — 일부러 배제하라\n- \"이건 당신을 위한 게 아닙니다\"라고 말할 수 있어야 진짜 팬이 생긴다.\n- 타깃을 좁히고 배제할수록 남은 사람들의 충성·전파력이 커진다.\n\n## 10. 실제 사례 (책 속)\n- 크리스피 크림(갓 구운 도넛 경험), 제트블루(위트·디자인), 스타벅스(제3의 공간), 더치보이 페인트(비틀어 따는 용기), 에어론 체어(지위의 상징).\n- 공통점: 광고가 아니라 제품·경험·디자인에 리마커블함을 내장.\n\n## 11. 측정하고 반복하라\n- 리마커블은 운이 아니라 과정. 작게 시도→측정→통하면 키우기.\n- 보랏빛 소도 시간이 지나면 평범해진다 → 계속 새 보랏빛 소를 만들어라.\n\n## 12. 유튜브·콘텐츠 적용\n- 썸네일·제목·도입부 3초가 보랏빛 소여야 한다. 무난하면 스크롤된다.\n- 모두가 좋아할 안전한 주제보다 특정 시청자가 열광할 뾰족한 관점을.\n- 영상마다 \"이거 봐!\" 하고 공유할 단 하나의 훅을 심어라. 바이럴은 설계다.\n\n## 13. 1인 기업 적용\n- 내 서비스가 \"또 하나의 비슷한 것\"이면 마케팅으로 못 살린다. 제품을 먼저 리마커블하게.\n- 작게 시작하되 한 축에서 극단적으로 달라라. 첫 고객을 열광하는 팬으로 → 무료 영업사원(스니저)이 된다.\n- 안전하게 가려는 본능을 의심하라. 가장 안전한 선택이 보통 가장 안 보이는 선택이다.\n\n## 한 줄 요약\n평범하면 안 보인다. 제품을 리마커블하게 만들고, 그것에 열광할 오타쿠를 노려라. 그들이 스니저가 되어 퍼뜨린다. 모두를 위하지 말고, 가장자리를 점령하라. 안전함이 가장 위험하다.",
    "tags": [
      "보랏빛",
      "가장",
      "제품",
      "purple",
      "cow",
      "않는다"
    ],
    "ts": 1781715260549,
    "category": "marketing",
    "source": "ezerai",
    "verified": true
  },
  {
    "id": "n17817152701483837",
    "text": "# MrBeast 후킹 로직\n# MrBeast 후킹 로직 분석\n\n## 핵심 패턴\n- **첫 5초**: 충격적 행동·결과 미리보기 (\"우리는 이 사람에게 100만 달러를 줬어요...\")\n- **5~30초**: 위기 설정·이해관계 명시 (\"...하지만 조건이 있죠.\")\n- **고밀도 컷**: 평균 1.5초당 1컷, 시선 못 떼게\n- **숫자 강조**: 항상 구체적 수치 (\"100만 달러\", \"24시간\", \"7명\")\n\n## 적용 체크리스트\n- [ ] 첫 5초에 결과 미리보기 있나?\n- [ ] 시청자가 \"이게 진짜?\" 의심하게 만드나?\n- [ ] 30초 안에 위기·이해관계 명확한가?\n- [ ] 컷 평균 길이가 2초 이하인가?",
    "tags": [
      "100",
      "mrbeast",
      "후킹",
      "로직",
      "결과",
      "미리보기"
    ],
    "ts": 1781715270149,
    "category": "marketing",
    "source": "ezerai",
    "verified": true
  },
  {
    "id": "n17817153331381603",
    "text": "# 스킬: 🎬 후킹 분석기\n본인 채널 최근 영상의 첫 30초 후킹 패턴을 자동 분석.\n실행 가능한 파이썬 스킬: <run>python3 \"C:\\Users\\mine2\\코다리부장\\Connect AI\\scripts\\_company\\connect-ai-packs\\스킬\\youtube\\hook_analyzer.py\"</run>",
    "tags": [
      "스킬",
      "후킹",
      "run",
      "connect",
      "분석기",
      "본인"
    ],
    "ts": 1781715333138,
    "category": "marketing",
    "source": "ezerai",
    "verified": true
  }
]